{"stats":{"minecraft:killed":{"minecraft:tropical_fish":10},"minecraft:custom":{"minecraft:interact_with_anvil":2,"minecraft:mob_kills":10,"minecraft:inspect_hopper":7,"minecraft:open_barrel":16,"minecraft:open_shulker_box":10,"minecraft:leave_game":81,"minecraft:time_since_death":93418,"minecraft:climb_one_cm":807,"minecraft:sprint_one_cm":2784247,"minecraft:walk_one_cm":1482170,"minecraft:drop":75,"minecraft:play_time":3650994,"minecraft:deaths":58,"minecraft:sneak_time":108207,"minecraft:walk_under_water_one_cm":22379,"minecraft:jump":19676,"minecraft:interact_with_blast_furnace":2,"minecraft:walk_on_water_one_cm":98757,"minecraft:total_world_time":513037,"minecraft:interact_with_furnace":1,"minecraft:interact_with_loom":1,"minecraft:pot_flower":38,"minecraft:time_since_rest":93420,"minecraft:open_enderchest":2,"minecraft:damage_taken":560,"minecraft:damage_dealt":377,"minecraft:interact_with_beacon":1,"minecraft:swim_one_cm":1602,"minecraft:fly_one_cm":82276469,"minecraft:open_chest":16,"minecraft:crouch_one_cm":24533,"minecraft:interact_with_smoker":1,"minecraft:fall_one_cm":15099},"minecraft:dropped":{"minecraft:water_bucket":1,"minecraft:diamond":1,"minecraft:yellow_concrete":1,"minecraft:cobblestone":1,"minecraft:deepslate_tile_wall":1,"minecraft:red_wool":1,"minecraft:grass_block":2,"minecraft:deepslate_tile_stairs":1,"minecraft:gray_concrete":64,"minecraft:sponge":64,"minecraft:smooth_quartz":1,"minecraft:smooth_stone":64,"minecraft:gold_ingot":13,"minecraft:lever":64,"minecraft:player_head":1,"minecraft:cocoa_beans":6,"minecraft:smooth_stone_slab":1,"minecraft:deepslate_brick_slab":64,"minecraft:quartz_bricks":1,"minecraft:debug_stick":1,"minecraft:oak_sign":16,"minecraft:salmon":6,"minecraft:poppy":26,"minecraft:diamond_sword":1,"minecraft:spruce_planks":1,"minecraft:stone_brick_stairs":1,"minecraft:white_stained_glass":1},"minecraft:picked_up":{"minecraft:cocoa_beans":5,"minecraft:turtle_helmet":1,"minecraft:potion":1,"minecraft:stone_brick_stairs":1,"minecraft:cornflower":1,"minecraft:item_frame":65,"minecraft:white_carpet":1,"minecraft:oak_sign":1,"minecraft:spruce_planks":1,"minecraft:rose_bush":2,"minecraft:player_head":1,"minecraft:poppy":19,"minecraft:sugar_cane":4,"minecraft:stone_button":2,"minecraft:trident":1,"minecraft:cobblestone":1,"minecraft:cooked_beef":2,"minecraft:glow_ink_sac":1,"minecraft:salmon":3,"minecraft:dirt":1,"minecraft:gray_carpet":3,"minecraft:kelp":7,"minecraft:bamboo":72,"minecraft:debug_stick":1,"minecraft:cooked_porkchop":2,"minecraft:sand":191,"minecraft:quartz_bricks":1,"minecraft:yellow_carpet":1,"minecraft:diamond":1},"minecraft:used":{"minecraft:oak_fence":90,"minecraft:oak_trapdoor":262,"minecraft:peony":1,"minecraft:trident":17,"minecraft:blue_terracotta":110,"minecraft:jungle_leaves":33,"minecraft:rose_bush":5,"minecraft:writable_book":2,"minecraft:iron_bars":937,"minecraft:brain_coral_fan":23,"minecraft:flint_and_steel":1,"minecraft:light_gray_stained_glass_pane":11,"minecraft:melon":8,"minecraft:spruce_slab":383,"minecraft:light_gray_carpet":89,"minecraft:oak_sign":82,"minecraft:white_concrete_powder":25,"minecraft:spruce_planks":2697,"minecraft:chest":12,"minecraft:stone":14062,"minecraft:quartz_stairs":538,"minecraft:bubble_coral":5,"minecraft:tube_coral":8,"minecraft:green_terracotta":2,"minecraft:netherrack":1,"minecraft:debug_stick":653,"minecraft:oak_door":2,"minecraft:torch":34,"minecraft:brewing_stand":3,"minecraft:dirt":7769,"minecraft:lily_of_the_valley":4,"minecraft:white_carpet":20,"minecraft:hopper":8,"minecraft:jungle_planks":23,"minecraft:spruce_stairs":59,"minecraft:deepslate_brick_slab":6,"minecraft:cobblestone_wall":2351,"minecraft:carrot":7,"minecraft:oak_wood":126,"minecraft:stone_stairs":297,"minecraft:pink_terracotta":3,"minecraft:jungle_trapdoor":64,"minecraft:spruce_fence":6,"minecraft:light_blue_stained_glass":184,"minecraft:stripped_spruce_log":101,"minecraft:andesite_wall":4,"minecraft:purple_stained_glass_pane":9,"minecraft:glass":546,"minecraft:stone_brick_slab":1833,"minecraft:dark_oak_planks":41,"minecraft:sea_lantern":410,"minecraft:cyan_terracotta":494,"minecraft:bricks":3,"minecraft:light_gray_stained_glass":20,"minecraft:red_tulip":62,"minecraft:quartz_pillar":616,"minecraft:iron_block":48,"minecraft:red_wool":713,"minecraft:yellow_stained_glass":2,"minecraft:quartz_slab":1474,"minecraft:spruce_wood":241,"minecraft:lantern":43,"minecraft:grass_block":16292,"minecraft:oak_stairs":19,"minecraft:crimson_slab":27,"minecraft:polished_andesite_stairs":81,"minecraft:quartz_block":159,"minecraft:warped_nylium":17,"minecraft:netherite_hoe":10,"minecraft:dark_oak_slab":361,"minecraft:mossy_cobblestone_slab":1,"minecraft:smooth_quartz":4947,"minecraft:tropical_fish_spawn_egg":10,"minecraft:pink_stained_glass_pane":68,"minecraft:pink_wool":340,"minecraft:crimson_planks":10,"minecraft:stone_brick_stairs":2956,"minecraft:barrel":13,"minecraft:stone_bricks":23695,"minecraft:blue_banner":6,"minecraft:item_frame":124,"minecraft:bamboo":49,"minecraft:bedrock":2,"minecraft:light_gray_wool":2,"minecraft:basalt":2516,"minecraft:glowstone":81,"minecraft:red_carpet":21,"minecraft:redstone_lamp":112,"minecraft:brown_carpet":5,"minecraft:black_stained_glass":2,"minecraft:horn_coral":16,"minecraft:hay_block":1,"minecraft:iron_trapdoor":525,"minecraft:dark_oak_pressure_plate":22,"minecraft:furnace":2,"minecraft:deepslate_tile_stairs":5,"minecraft:gold_block":39,"minecraft:stone_pressure_plate":2,"minecraft:potato":6,"minecraft:acacia_planks":10,"minecraft:orange_terracotta":8,"minecraft:seagrass":64,"minecraft:dark_prismarine_stairs":10,"minecraft:horn_coral_fan":2,"minecraft:knowledge_book":1,"minecraft:calcite":48,"minecraft:quartz_bricks":86,"minecraft:dark_oak_stairs":31,"minecraft:water_bucket":762,"minecraft:mossy_stone_bricks":53,"minecraft:end_rod":25,"minecraft:diorite":5,"minecraft:tube_coral_fan":7,"minecraft:cobblestone_stairs":3850,"minecraft:pink_glazed_terracotta":51,"minecraft:lodestone":289,"minecraft:birch_planks":2,"minecraft:red_stained_glass":23,"minecraft:polished_andesite":1416,"minecraft:gray_carpet":264,"minecraft:blackstone_stairs":801,"minecraft:oak_planks":30,"minecraft:bubble_coral_fan":4,"minecraft:blackstone":20286,"minecraft:lime_concrete_powder":1,"minecraft:jungle_pressure_plate":4,"minecraft:redstone_block":70,"minecraft:spruce_sign":5,"minecraft:cauldron":3,"minecraft:clay":68,"minecraft:beacon":3,"minecraft:cobblestone_slab":4755,"minecraft:sugar_cane":36,"minecraft:deepslate_bricks":1,"minecraft:smooth_quartz_stairs":11,"minecraft:cracked_stone_bricks":39,"minecraft:polished_blackstone_bricks":372,"minecraft:oak_leaves":5012,"minecraft:white_wool":141,"minecraft:brain_coral":10,"minecraft:polished_blackstone_pressure_plate":3,"minecraft:mossy_cobblestone":44,"minecraft:dark_oak_trapdoor":14,"minecraft:sand":2500,"minecraft:lime_terracotta":2,"minecraft:vine":119,"minecraft:dark_prismarine_slab":46,"minecraft:tnt":39,"minecraft:oak_slab":63,"minecraft:loom":3,"minecraft:light_blue_wool":13,"minecraft:birch_sign":11,"minecraft:blast_furnace":19,"minecraft:yellow_concrete":302,"minecraft:acacia_leaves":173,"minecraft:campfire":1,"minecraft:sponge":28,"minecraft:fire_coral":4,"minecraft:stone_brick_wall":972,"minecraft:gray_concrete":3956,"minecraft:spruce_log":6,"minecraft:black_concrete_powder":1,"minecraft:infested_stone_bricks":1535,"minecraft:smoker":6,"minecraft:cake":2,"minecraft:warped_planks":721,"minecraft:deepslate_tile_wall":6,"minecraft:black_concrete":57,"minecraft:sticky_piston":19,"minecraft:birch_fence":5,"minecraft:redstone_torch":1,"minecraft:oak_log":489,"minecraft:cornflower":75,"minecraft:dark_prismarine":78,"minecraft:netherite_block":26,"minecraft:green_concrete":1,"minecraft:piston":93,"minecraft:lever":20,"minecraft:flower_pot":80,"minecraft:light":1,"minecraft:black_wool":49,"minecraft:oxeye_daisy":64,"minecraft:acacia_door":18,"minecraft:dark_oak_log":7,"minecraft:gray_stained_glass_pane":48,"minecraft:light_gray_concrete":12,"minecraft:birch_slab":3,"minecraft:heavy_weighted_pressure_plate":11,"minecraft:nether_sprouts":1,"minecraft:barrier":89,"minecraft:warped_slab":54,"minecraft:string":101,"minecraft:stone_button":114,"minecraft:jungle_stairs":28,"minecraft:stone_slab":53,"minecraft:spruce_trapdoor":65,"minecraft:iron_door":29,"minecraft:gravel":23,"minecraft:polished_andesite_slab":172,"minecraft:soul_lantern":8,"minecraft:blackstone_slab":17,"minecraft:green_carpet":12,"minecraft:blue_carpet":98,"minecraft:chiseled_stone_bricks":1028,"minecraft:jungle_sign":33,"minecraft:diamond_sword":10,"minecraft:coal_block":114,"minecraft:cobblestone":19076,"minecraft:potion":6,"minecraft:pufferfish_bucket":11,"minecraft:crimson_stairs":5,"minecraft:grindstone":1,"minecraft:stripped_oak_wood":4,"minecraft:dark_oak_fence":40,"minecraft:white_stained_glass":81,"minecraft:pink_shulker_box":6,"minecraft:ice":42,"minecraft:green_concrete_powder":82,"minecraft:red_banner":19,"minecraft:andesite":67,"minecraft:chain":28,"minecraft:glass_pane":1579,"minecraft:pink_stained_glass":74,"minecraft:smooth_stone_slab":1455,"minecraft:polished_blackstone_button":11,"minecraft:sea_pickle":9,"minecraft:tropical_fish_bucket":15,"minecraft:stripped_oak_log":17,"minecraft:white_concrete":1002,"minecraft:kelp":45,"minecraft:dandelion":70,"minecraft:bone_meal":2,"minecraft:smooth_stone":1632,"minecraft:splash_potion":108,"minecraft:soul_torch":30,"minecraft:gray_stained_glass":1053}},"DataVersion":2730}