{"stats":{"minecraft:killed_by":{"minecraft:player":1},"minecraft:mined":{"minecraft:rail":1,"minecraft:sand":10},"minecraft:used":{"minecraft:diorite_stairs":23,"minecraft:oak_trapdoor":95,"minecraft:peony":13,"minecraft:oak_fence":34,"minecraft:jungle_leaves":36,"minecraft:blue_terracotta":4,"minecraft:rose_bush":3,"minecraft:iron_bars":19,"minecraft:orange_concrete":1,"minecraft:white_tulip":95,"minecraft:red_concrete":145,"minecraft:spruce_slab":338,"minecraft:oak_sign":30,"minecraft:light_blue_terracotta":3,"minecraft:polished_basalt":43,"minecraft:chest":10,"minecraft:spruce_planks":318,"minecraft:brown_concrete":7,"minecraft:stone":228,"minecraft:quartz_stairs":28,"minecraft:stripped_birch_wood":134,"minecraft:smooth_sandstone_stairs":11,"minecraft:green_terracotta":1172,"minecraft:oak_door":2,"minecraft:debug_stick":35,"minecraft:anvil":1,"minecraft:lily_of_the_valley":159,"minecraft:target":37,"minecraft:white_carpet":6,"minecraft:hopper":10,"minecraft:brick_slab":244,"minecraft:spruce_stairs":385,"minecraft:oak_wood":124,"minecraft:acacia_button":8,"minecraft:spruce_fence":95,"minecraft:azure_bluet":86,"minecraft:blue_concrete":80,"minecraft:birch_door":2,"minecraft:andesite_wall":136,"minecraft:polished_blackstone_slab":16,"minecraft:stone_brick_slab":36,"minecraft:dark_oak_planks":12,"minecraft:sea_lantern":10,"minecraft:lava_bucket":1,"minecraft:cyan_terracotta":128,"minecraft:bricks":891,"minecraft:netherite_shovel":5,"minecraft:stripped_dark_oak_wood":40,"minecraft:bookshelf":12,"minecraft:red_tulip":3,"minecraft:quartz_pillar":129,"minecraft:lantern":88,"minecraft:quartz_slab":66,"minecraft:black_stained_glass_pane":86,"minecraft:iron_block":8,"minecraft:grass_block":3057,"minecraft:oak_stairs":16,"minecraft:brick_stairs":476,"minecraft:smooth_sandstone":1129,"minecraft:dark_oak_leaves":24,"minecraft:smooth_quartz":233,"minecraft:diorite_wall":6,"minecraft:stone_brick_stairs":108,"minecraft:barrel":52,"minecraft:stone_bricks":54,"minecraft:item_frame":21,"minecraft:light_gray_wool":28,"minecraft:birch_trapdoor":42,"minecraft:tripwire_hook":7,"minecraft:red_carpet":41,"minecraft:redstone_lamp":50,"minecraft:brown_carpet":83,"minecraft:bow":387,"minecraft:tall_grass":10,"minecraft:iron_trapdoor":11,"minecraft:infested_cracked_stone_bricks":2,"minecraft:oak_sapling":30,"minecraft:furnace":25,"minecraft:minecart":1,"minecraft:polished_diorite_stairs":74,"minecraft:acacia_wood":48,"minecraft:trapped_chest":6,"minecraft:orange_terracotta":1,"minecraft:turtle_egg":8,"minecraft:enchanted_golden_apple":1,"minecraft:large_fern":125,"minecraft:polished_blackstone_stairs":28,"minecraft:light_blue_carpet":6,"minecraft:water_bucket":3,"minecraft:cobblestone_stairs":9,"minecraft:sandstone_stairs":48,"minecraft:brick_wall":182,"minecraft:spruce_door":20,"minecraft:birch_planks":83,"minecraft:stripped_birch_log":1,"minecraft:glass_bottle":1,"minecraft:dark_oak_sign":2,"minecraft:gray_carpet":7,"minecraft:blackstone_stairs":4,"minecraft:cartography_table":3,"minecraft:blue_wool":3,"minecraft:andesite_slab":135,"minecraft:smooth_sandstone_slab":8,"minecraft:sandstone":4,"minecraft:composter":7,"minecraft:cauldron":4,"minecraft:spruce_sign":9,"minecraft:fletching_table":2,"minecraft:spruce_fence_gate":6,"minecraft:oak_leaves":709,"minecraft:cracked_stone_bricks":2,"minecraft:smooth_quartz_stairs":136,"minecraft:white_wool":6,"minecraft:yellow_terracotta":1,"minecraft:dark_oak_trapdoor":32,"minecraft:rail":1,"minecraft:sand":13,"minecraft:stripped_dark_oak_log":586,"minecraft:terracotta":87,"minecraft:vine":13,"minecraft:crafting_table":4,"minecraft:loom":2,"minecraft:birch_sign":33,"minecraft:blast_furnace":5,"minecraft:light_gray_terracotta":79,"minecraft:yellow_concrete":230,"minecraft:crossbow":128,"minecraft:campfire":18,"minecraft:light_gray_concrete_powder":366,"minecraft:blackstone_wall":2,"minecraft:note_block":8,"minecraft:stone_brick_wall":66,"minecraft:gray_concrete":108,"minecraft:painting":15,"minecraft:smoker":13,"minecraft:birch_fence":23,"minecraft:redstone_torch":7,"minecraft:oak_log":210,"minecraft:gray_terracotta":239,"minecraft:green_concrete":30,"minecraft:flower_pot":8,"minecraft:black_concrete":506,"minecraft:firework_rocket":2,"minecraft:oxeye_daisy":95,"minecraft:daylight_detector":15,"minecraft:light_gray_concrete":363,"minecraft:command_block":7,"minecraft:birch_slab":63,"minecraft:heavy_weighted_pressure_plate":14,"minecraft:map":6,"minecraft:oak_button":2,"minecraft:stone_button":41,"minecraft:cyan_concrete":1,"minecraft:red_terracotta":1,"minecraft:spruce_trapdoor":364,"minecraft:oak_pressure_plate":20,"minecraft:iron_door":12,"minecraft:gravel":30,"minecraft:polished_andesite_slab":388,"minecraft:pufferfish":3,"minecraft:fishing_rod":317,"minecraft:cobblestone":6,"minecraft:potion":2,"minecraft:smithing_table":1,"minecraft:stripped_oak_wood":1,"minecraft:grindstone":11,"minecraft:andesite":8,"minecraft:bucket":1,"minecraft:green_concrete_powder":23,"minecraft:white_stained_glass":1,"minecraft:andesite_stairs":296,"minecraft:sandstone_slab":21,"minecraft:chain":10,"minecraft:glass_pane":336,"minecraft:smooth_stone_slab":176,"minecraft:oak_boat":1,"minecraft:sea_pickle":13,"minecraft:white_concrete":736,"minecraft:coarse_dirt":2,"minecraft:splash_potion":1,"minecraft:smooth_stone":15,"minecraft:bone_meal":215,"minecraft:cobweb":6,"minecraft:birch_stairs":12},"minecraft:crafted":{"minecraft:firework_star":1,"minecraft:firework_rocket":192},"minecraft:custom":{"minecraft:interact_with_anvil":1,"minecraft:interact_with_crafting_table":4,"minecraft:open_barrel":10,"minecraft:fill_cauldron":3,"minecraft:interact_with_campfire":19,"minecraft:leave_game":16,"minecraft:time_since_death":309671,"minecraft:climb_one_cm":84,"minecraft:sprint_one_cm":2050153,"minecraft:walk_one_cm":1292067,"minecraft:drop":10,"minecraft:target_hit":324,"minecraft:deaths":8,"minecraft:walk_under_water_one_cm":1197,"minecraft:sneak_time":24418,"minecraft:boat_one_cm":36078,"minecraft:jump":6451,"minecraft:interact_with_blast_furnace":4,"minecraft:walk_on_water_one_cm":7626,"minecraft:interact_with_furnace":4,"minecraft:tune_noteblock":8,"minecraft:play_one_minute":2191229,"minecraft:pot_flower":8,"minecraft:interact_with_grindstone":10,"minecraft:time_since_rest":309673,"minecraft:damage_taken":2218,"minecraft:open_enderchest":2,"minecraft:minecart_one_cm":2425,"minecraft:fly_one_cm":11946488,"minecraft:open_chest":4,"minecraft:crouch_one_cm":22046,"minecraft:aviate_one_cm":1582270,"minecraft:fish_caught":9,"minecraft:fall_one_cm":17900},"minecraft:broken":{"minecraft:fishing_rod":2},"minecraft:dropped":{"minecraft:crossbow":2,"minecraft:black_concrete":1,"minecraft:smooth_stone":2,"minecraft:bricks":1,"minecraft:enchanted_golden_apple":1,"minecraft:debug_stick":1,"minecraft:turtle_helmet":2},"minecraft:picked_up":{"minecraft:chicken":4,"minecraft:turtle_helmet":1,"minecraft:potion":1,"minecraft:item_frame":3,"minecraft:white_stained_glass":1,"minecraft:pufferfish":3,"minecraft:oak_sign":1,"minecraft:sea_pickle":4,"minecraft:smooth_stone":2,"minecraft:beef":4,"minecraft:enchanted_golden_apple":1,"minecraft:stick":13,"minecraft:bowl":1,"minecraft:porkchop":6,"minecraft:stone_button":2,"minecraft:mutton":3,"minecraft:cod":6,"minecraft:sponge":64,"minecraft:iron_door":1,"minecraft:tripwire_hook":1,"minecraft:salmon":2,"minecraft:lantern":26,"minecraft:light_gray_concrete_powder":3,"minecraft:apple":1,"minecraft:gray_carpet":2,"minecraft:debug_stick":1,"minecraft:dark_oak_slab":1,"minecraft:oak_pressure_plate":3,"minecraft:sand":170,"minecraft:spruce_door":2,"minecraft:black_concrete":1,"minecraft:birch_sign":4,"minecraft:lever":64,"minecraft:crossbow":1,"minecraft:spruce_sign":3,"minecraft:oak_sapling":26,"minecraft:bricks":1}},"DataVersion":2586}